cXpdfPython.cpython-310-darwin.so
freetype/.DS_Store
freetype/.clang-format
freetype/.git
freetype/.gitignore
freetype/.gitlab-ci.yml
freetype/.gitmodules
freetype/.mailmap
freetype/CMakeLists.txt
freetype/LICENSE.TXT
freetype/Makefile
freetype/README
freetype/README.git
freetype/autogen.sh
freetype/config.mk
freetype/configure
freetype/meson.build
freetype/meson_options.txt
freetype/modules.cfg
freetype/vms_make.com
freetype/builds/mac/ascii2mpw.py
freetype/builds/meson/extract_freetype_version.py
freetype/builds/meson/extract_libtool_version.py
freetype/builds/meson/generate_reference_docs.py
freetype/builds/meson/parse_modules_cfg.py
freetype/builds/meson/process_ftoption_h.py
freetype/include/ft2build.h
freetype/include/dlg/dlg.h
freetype/include/dlg/output.h
freetype/include/freetype/freetype.h
freetype/include/freetype/ftadvanc.h
freetype/include/freetype/ftbbox.h
freetype/include/freetype/ftbdf.h
freetype/include/freetype/ftbitmap.h
freetype/include/freetype/ftbzip2.h
freetype/include/freetype/ftcache.h
freetype/include/freetype/ftchapters.h
freetype/include/freetype/ftcid.h
freetype/include/freetype/ftcolor.h
freetype/include/freetype/ftdriver.h
freetype/include/freetype/fterrdef.h
freetype/include/freetype/fterrors.h
freetype/include/freetype/ftfntfmt.h
freetype/include/freetype/ftgasp.h
freetype/include/freetype/ftglyph.h
freetype/include/freetype/ftgxval.h
freetype/include/freetype/ftgzip.h
freetype/include/freetype/ftimage.h
freetype/include/freetype/ftincrem.h
freetype/include/freetype/ftlcdfil.h
freetype/include/freetype/ftlist.h
freetype/include/freetype/ftlogging.h
freetype/include/freetype/ftlzw.h
freetype/include/freetype/ftmac.h
freetype/include/freetype/ftmm.h
freetype/include/freetype/ftmodapi.h
freetype/include/freetype/ftmoderr.h
freetype/include/freetype/ftotval.h
freetype/include/freetype/ftoutln.h
freetype/include/freetype/ftparams.h
freetype/include/freetype/ftpfr.h
freetype/include/freetype/ftrender.h
freetype/include/freetype/ftsizes.h
xpydf-0.1.6.dist-info/LICENSE
xpydf-0.1.6.dist-info/METADATA
xpydf-0.1.6.dist-info/WHEEL
xpydf-0.1.6.dist-info/top_level.txt
xpydf-0.1.6.dist-info/RECORD
