Metadata-Version: 2.1
Name: xpydf
Version: 0.1.6
Summary: Python wrapper around the pdftotext and pdfimages functionalities of xpdf.
Author-email: Matthijs Wesseling <matthijs.wesseling@bigdatarepublic.nl>
Project-URL: Homepage, https://github.com/Bladieblah/xpdf-python
Project-URL: Bug Tracker, https://github.com/Bladieblah/xpdf-python/issues
Classifier: Programming Language :: Python :: 3
Classifier: Operating System :: OS Independent
Classifier: License :: OSI Approved :: GNU General Public License v3 (GPLv3)
Requires-Python: >=3.7
License-File: LICENSE
Requires-Dist: numpy (>=1.21.6)
